peakrdl_python_simple/__init__.py
peakrdl_python_simple/__peakrdl__.py
peakrdl_python_simple/exporter.py
peakrdl_python_simple/py.typed
peakrdl_python_simple/regif/__init__.py
peakrdl_python_simple/regif/__main__.py
peakrdl_python_simple/regif/access.py
peakrdl_python_simple/regif/impl/__init__.py
peakrdl_python_simple/regif/impl/devmem.py
peakrdl_python_simple/regif/impl/dummy.py
peakrdl_python_simple/regif/impl/mmap.py
peakrdl_python_simple/regif/impl/multiregion.py
peakrdl_python_simple/regif/impl/socket.py
peakrdl_python_simple/regif/regif.py
peakrdl_python_simple/regif/spec.py
peakrdl_python_simple-0.2.14.dist-info/LICENSE
peakrdl_python_simple-0.2.14.dist-info/METADATA
peakrdl_python_simple-0.2.14.dist-info/WHEEL
peakrdl_python_simple-0.2.14.dist-info/entry_points.txt
peakrdl_python_simple-0.2.14.dist-info/RECORD
