Metadata-Version: 2.1
Name: peakrdl_python_simple
Version: 0.2.14
Summary: Export Python description from the systemrdl-compiler register model
Home-page: https://github.com/MarekPikula/PeakRDL-Python-simple
License: GPL-3.0-only
Author: Marek Pikuła
Author-email: marek.pikula@embevity.com
Maintainer: Marek Pikuła
Maintainer-email: marek.pikula@embevity.com
Requires-Python: >=3.7.2,<4.0.0
Classifier: Development Status :: 4 - Beta
Classifier: Intended Audience :: Developers
Classifier: License :: OSI Approved :: GNU General Public License v3 (GPLv3)
Classifier: Operating System :: OS Independent
Classifier: Programming Language :: Python :: 3
Classifier: Programming Language :: Python :: 3.8
Classifier: Programming Language :: Python :: 3.9
Classifier: Programming Language :: Python :: 3.10
Classifier: Programming Language :: Python :: 3.11
Classifier: Topic :: Scientific/Engineering :: Electronic Design Automation (EDA)
Provides-Extra: cli
Provides-Extra: generator
Provides-Extra: tracing
Requires-Dist: loguru (>=0.6.0,<0.7.0) ; extra == "tracing"
Requires-Dist: peakrdl (>=0.9.0,<0.10.0) ; extra == "cli"
Requires-Dist: systemrdl-compiler (>=1.25.0,<2.0.0) ; extra == "generator" or extra == "cli"
Project-URL: Documentation, https://peakrdl-python-simple.readthedocs.io
Project-URL: Repository, https://github.com/MarekPikula/PeakRDL-Python-simple
